Metadata-Version: 2.4
Name: eshopbox
Version: 1.1.8
Summary: Python SDK for EShopBox Shipping APIs
Home-page: https://github.com/onesakib/eshopbox
Author: Sakib Malik
Author-email: Sakib Malik <sakibmaliknakur347@gmail.com>
License: MIT
Project-URL: Homepage, https://github.com/onesakib/eshopbox
Project-URL: Documentation, https://eshopbox.readthedocs.io
Project-URL: Repository, https://github.com/onesakib/eshopbox
Keywords: eshopbox,shipping,logistics,api,sdk
Classifier: Development Status :: 4 - Beta
Classifier: Intended Audience :: Developers
Classifier: License :: OSI Approved :: MIT License
Classifier: Programming Language :: Python :: 3
Classifier: Programming Language :: Python :: 3.8
Classifier: Programming Language :: Python :: 3.9
Classifier: Programming Language :: Python :: 3.10
Classifier: Programming Language :: Python :: 3.11
Requires-Python: >=3.8
License-File: LICENSE
Requires-Dist: requests>=2.28.0
Requires-Dist: python-dateutil>=2.8.0
Provides-Extra: dev
Requires-Dist: pytest>=7.0; extra == "dev"
Requires-Dist: pytest-cov>=4.0; extra == "dev"
Requires-Dist: black>=22.0; extra == "dev"
Requires-Dist: isort>=5.0; extra == "dev"
Requires-Dist: flake8>=5.0; extra == "dev"
Requires-Dist: mypy>=0.990; extra == "dev"
Requires-Dist: pre-commit>=2.20; extra == "dev"
Provides-Extra: docs
Requires-Dist: sphinx>=5.0; extra == "docs"
Requires-Dist: sphinx-rtd-theme>=1.0; extra == "docs"
Dynamic: license-file
Dynamic: requires-python
